<?xml version="1.0" encoding="UTF-8"?>
<metadata xml:lang="en"><Esri><CreaDate>20181116</CreaDate><CreaTime>09351600</CreaTime><ArcGISFormat>1.0</ArcGISFormat><SyncOnce>TRUE</SyncOnce><DataProperties><lineage><Process ToolSource="c:\program files (x86)\arcgis\desktop10.4\ArcToolbox\Toolboxes\Spatial Analyst Tools.tbx\Times" Date="20181116" Time="093516">Times E:/PaleoViewData/periods/H_M_8326y_4200yBP/bioclimsR3/mean/TEMP_ilUlv/bio_15.tif E:\PaleoViewData\PaleoViewMaskReadmes\mask\Mid_Holocene_Mask.tif E:\PaleoViewData\periods\H_M_8326y_4200yBP\bioclimsR3\mean\FINALS\2_5min\bio_15.tif</Process></lineage></DataProperties></Esri></metadata>
